virtmat/__init__.py
virtmat/constants/__init__.py
virtmat/functions/__init__.py
virtmat/functions/unumpy.py
virtmat/language/__init__.py
virtmat/language/cli/__init__.py
virtmat/language/cli/run_model.py
virtmat/language/cli/run_session.py
virtmat/language/cli/version.py
virtmat/language/constraints/__init__.py
virtmat/language/constraints/amml.py
virtmat/language/constraints/chem.py
virtmat/language/constraints/cyclic.py
virtmat/language/constraints/duplicates.py
virtmat/language/constraints/functions.py
virtmat/language/constraints/parallel.py
virtmat/language/constraints/processors.py
virtmat/language/constraints/typechecks.py
virtmat/language/constraints/units.py
virtmat/language/constraints/values.py
virtmat/language/constraints/view.py
virtmat/language/grammar/arrays.tx
virtmat/language/grammar/identifiers.tx
virtmat/language/grammar/imports.tx
virtmat/language/grammar/resources.tx
virtmat/language/grammar/semversion.tx
virtmat/language/grammar/session.tx
virtmat/language/grammar/types.tx
virtmat/language/grammar/virtmat.tx
virtmat/language/interpreter/__init__.py
virtmat/language/interpreter/deferred_executor.py
virtmat/language/interpreter/instant_executor.py
virtmat/language/interpreter/session.py
virtmat/language/interpreter/session_manager.py
virtmat/language/interpreter/workflow_executor.py
virtmat/language/kernel/__init__.py
virtmat/language/kernel/__main__.py
virtmat/language/kernel/install.py
virtmat/language/kernel/kernel.py
virtmat/language/kernel/logo-32x32.png
virtmat/language/kernel/logo-64x64.png
virtmat/language/metamodel/__init__.py
virtmat/language/metamodel/amml.py
virtmat/language/metamodel/clone.py
virtmat/language/metamodel/function.py
virtmat/language/metamodel/io.py
virtmat/language/metamodel/processors.py
virtmat/language/metamodel/properties.py
virtmat/language/metamodel/view.py
virtmat/language/metamodel/workflow.py
virtmat/language/schema/__init__.py
virtmat/language/schema/ammlobject.json
vre_language-0.7.0.dist-info/licenses/LICENSE
vre_language-0.7.0.dist-info/METADATA
vre_language-0.7.0.dist-info/WHEEL
vre_language-0.7.0.dist-info/entry_points.txt
vre_language-0.7.0.dist-info/top_level.txt
vre_language-0.7.0.dist-info/RECORD
