Metadata-Version: 2.4
Name: vre-language
Version: 0.7.0
Summary: Domain-specific languages and supporting tools for scientific computing
Author: The Virtmat Tools Team
Author-email: virtmat-tools@lists.kit.edu
License: BSD-3-Clause
Project-URL: Homepage, https://gitlab.kit.edu/kit/virtmat-tools/vre-language
Project-URL: Documentation, https://vre-language.readthedocs.io
Project-URL: Download, https://pypi.org/project/vre-language/#files
Project-URL: Source Code, https://gitlab.kit.edu/kit/virtmat-tools/vre-language
Project-URL: Bug Reports, https://gitlab.kit.edu/kit/virtmat-tools/vre-language/-/issues
Project-URL: Changelog, https://gitlab.kit.edu/kit/virtmat-tools/vre-language/-/blob/master/CHANGELOG.md
Project-URL: Credits, https://gitlab.kit.edu/kit/virtmat-tools/vre-language/-/blob/master/CREDITS.md
Project-URL: Contributing, https://gitlab.kit.edu/kit/virtmat-tools/vre-language/-/blob/master/CONTRIBUTING.md
Keywords: domain-specific language,scientific computing,workflow,Jupyter
Classifier: Development Status :: 4 - Beta
Classifier: Environment :: Web Environment
Classifier: Framework :: Jupyter
Classifier: Framework :: Jupyter :: JupyterLab
Classifier: Intended Audience :: Science/Research
Classifier: License :: OSI Approved :: BSD License
Classifier: Natural Language :: English
Classifier: Operating System :: OS Independent
Classifier: Programming Language :: Python
Classifier: Programming Language :: Python :: 3
Classifier: Programming Language :: Python :: 3.10
Classifier: Programming Language :: Python :: 3.11
Classifier: Programming Language :: Python :: 3.12
Classifier: Topic :: Scientific/Engineering
Classifier: Topic :: Software Development :: Interpreters
Classifier: Topic :: Software Development :: User Interfaces
Classifier: Topic :: Other/Nonlisted Topic
Requires-Python: >=3.10
License-File: LICENSE
Requires-Dist: textx
Requires-Dist: numpy
Requires-Dist: scipy
Requires-Dist: pandas>=2.2.0
Requires-Dist: pint>=0.24.3
Requires-Dist: pint-pandas>=0.7.1
Requires-Dist: uncertainties
Requires-Dist: seaborn
Requires-Dist: pyyaml
Requires-Dist: dill
Requires-Dist: vre-middleware>=1.3.0
Requires-Dist: fireworks>=2.0.6
Requires-Dist: fireworks-schema>=1.4.2
Requires-Dist: jsonschema>=4.18.0
Requires-Dist: jupyter_client
Requires-Dist: ipykernel
Requires-Dist: ase>=3.23.0
Provides-Extra: test
Requires-Dist: requests; extra == "test"
Requires-Dist: pytz; extra == "test"
Requires-Dist: python-dateutil; extra == "test"
Requires-Dist: flake8; extra == "test"
Requires-Dist: pylint; extra == "test"
Requires-Dist: pytest; extra == "test"
Requires-Dist: pylint-exit; extra == "test"
Requires-Dist: pytest-cov; extra == "test"
Requires-Dist: anybadge; extra == "test"
Requires-Dist: pyflakes; extra == "test"
Provides-Extra: mongomock
Requires-Dist: mongomock-persistence>=0.0.4; extra == "mongomock"
Dynamic: license-file
